chistes_hub_malaga/__init__.py
chistes_hub_malaga/functions.py
chistes_hub_malaga/main.py
chistes_hub_malaga-0.1.0.dist-info/WHEEL
chistes_hub_malaga-0.1.0.dist-info/METADATA
chistes_hub_malaga-0.1.0.dist-info/RECORD
