Metadata-Version: 2.1
Name: chistes-hub-malaga
Version: 0.1.0
Summary: 
Author: Pablo Martin Fernandez
Author-email: pablo.martin.fernandez@pwc.com
Requires-Python: >=3.8,<4.0
Classifier: Programming Language :: Python :: 3
Classifier: Programming Language :: Python :: 3.8
Classifier: Programming Language :: Python :: 3.9
Requires-Dist: googletrans (==4.0.0rc1)
Requires-Dist: requests (>=2.25.1,<3.0.0)
